pdf2dataset/__init__.py
pdf2dataset/distributor.py
pdf2dataset/downloader.py
pdf2dataset/logger.py
pdf2dataset/main.py
pdf2dataset/reader.py
pdf2dataset/writer.py
pdf2dataset_tools-1.0.2.data/data/README.md
pdf2dataset_tools-1.0.2.dist-info/LICENSE
pdf2dataset_tools-1.0.2.dist-info/METADATA
pdf2dataset_tools-1.0.2.dist-info/WHEEL
pdf2dataset_tools-1.0.2.dist-info/entry_points.txt
pdf2dataset_tools-1.0.2.dist-info/top_level.txt
pdf2dataset_tools-1.0.2.dist-info/RECORD
