Metadata-Version: 2.1
Name: pdf2dataset-tools
Version: 1.0.2
Summary: Easily turn a set of pdf urls to an pdf dataset.
Home-page: https://github.com/vinyesm/pdf2dataset
Author: Marina Vinyes
Author-email: vinyes.marina@gmail.com
License: MIT
Keywords: machine learning,text,download,pdf,dataset
Platform: UNKNOWN
Classifier: Development Status :: 4 - Beta
Classifier: Intended Audience :: Developers
Classifier: Topic :: Scientific/Engineering :: Artificial Intelligence
Classifier: License :: OSI Approved :: MIT License
Classifier: Programming Language :: Python :: 3.9
License-File: LICENSE
Requires-Dist: tqdm<5,>=4.62.3
Requires-Dist: fire<0.6.0,>=0.4.0
Requires-Dist: webdataset<0.3,>=0.2.5
Requires-Dist: pandas<3,>=1.1.5
Requires-Dist: pyarrow<16,>=6.0.1
Requires-Dist: albumentations<2,>=1.1.0
Requires-Dist: dataclasses<1.0.0,>=0.6
Requires-Dist: wandb<0.17,>=0.16.0
Requires-Dist: fsspec
Requires-Dist: pyspark
Requires-Dist: s3fs
